aioboto3_assume/__init__.py
aioboto3_assume/aio_assume_refresh.py
aioboto3_assume/core.py
aioboto3_assume/exceptions.py
aioboto3_assume-0.1.2.dist-info/licenses/LICENSE
aioboto3_assume-0.1.2.dist-info/METADATA
aioboto3_assume-0.1.2.dist-info/WHEEL
aioboto3_assume-0.1.2.dist-info/top_level.txt
aioboto3_assume-0.1.2.dist-info/RECORD
